MANIFEST.in
README.txt
buildout.cfg
setup.py
docs/LICENSE.GPL
docs/LICENSE.txt
src/themes/__init__.py
src/themes.realestate_ecuador.egg-info/PKG-INFO
src/themes.realestate_ecuador.egg-info/SOURCES.txt
src/themes.realestate_ecuador.egg-info/dependency_links.txt
src/themes.realestate_ecuador.egg-info/entry_points.txt
src/themes.realestate_ecuador.egg-info/namespace_packages.txt
src/themes.realestate_ecuador.egg-info/not-zip-safe
src/themes.realestate_ecuador.egg-info/requires.txt
src/themes.realestate_ecuador.egg-info/top_level.txt
src/themes/realestate_ecuador/__init__.py
src/themes/realestate_ecuador/i18n.py
src/themes/realestate_ecuador/interfaces.py
src/themes/realestate_ecuador/testing.py
src/themes/realestate_ecuador/browser/__init__.py
src/themes/realestate_ecuador/browser/controlpanel.py
src/themes/realestate_ecuador/browser/frontpage.py
src/themes/realestate_ecuador/browser/interfaces.py
src/themes/realestate_ecuador/browser/viewlets.py
src/themes/realestate_ecuador/tests/__init__.py
src/themes/realestate_ecuador/tests/test_example.py