Metadata-Version: 1.0
Name: themes.realestate-ecuador
Version: 0.3
Summary: Theme for Real Estate Agents
Home-page: http://svn.plone.org/svn/collective/
Author: Jens Krause
Author-email: jens@propertyshelf.com
License: gpl
Keywords: Real Estate
Platform: UNKNOWN
Classifier: Programming Language :: Python
